riksdagenapi/__init__.py
riksdagenapi/dokument.py
riksdagenapi/dokumentlista.py
riksdagenapi/exceptions.py
riksdagenapi-0.0.4.dist-info/LICENSE
riksdagenapi-0.0.4.dist-info/METADATA
riksdagenapi-0.0.4.dist-info/WHEEL
riksdagenapi-0.0.4.dist-info/RECORD
